[{
    "centerX": "119.43524168161399",
    "centerY": "32.387308706499994",
    "count": 0,
    "createDate": "2018-09-21 15:48:38",
    "createUser": "Dyzgldg001",
    "gisType": "3D",
    "id": 39763,
    "isDeleted": 0,
    "maxLat": 32.38881074354833,
    "maxLon": 119.436325294056,
    "minLat": 32.38638602659887,
    "minLon": 119.433804017582,
    "orgInternalCode": ".1.10.1.1.5.10.",
    "organization": {
        "createDate": "2015-12-22 17:29:19",
        "createUser": "Dyzgldg001",
        "departmentNo": "321002001006009",
        "fullPinyin": "dishiwangge",
        "gridGatetory": 0,
        "gridProperty": 0,
        "gridPropertyLabel": "城市网格",
        "hasJudgeAuthorize": false,
        "homePageVersion": 0,
        "id": 136964,
        "maxCode": 0,
        "navigationVersion": 1,
        "newDepartmentNo": "321002001006010",
        "orgInternalCode": ".1.10.1.1.5.10.",
        "orgLevel": {
            "displaySeq": 0,
            "id": 207,
            "internalId": 0
        },
        "orgName": "第十网格",
        "orgType": {
            "displaySeq": 0,
            "id": 214,
            "internalId": 0
        },
        "parentOrg": {
            "gridPropertyLabel": "城市网格",
            "id": 21199,
            "maxCode": 0
        },
        "seq": 10,
        "simplePinyin": "dswg",
        "subCount": 0,
        "subCountFun": 0,
        "updateDate": "2019-07-25 16:19:51",
        "updateUser": "Byzgl001"
    },
    "points": "POLYGON((119.43618581918723 32.38881074354833,119.43540261415488 32.388531793810785,119.43479107049949 32.387995352007806,119.43469451097495 32.38788806364721,119.43459795145041 32.387534012057245,119.43444774774558 32.38708340094274,119.43435118822104 32.38693319723791,119.433804017582 32.38690101072973,119.43381474641807 32.38665424750036,119.43476961282737 32.38666497633642,119.4348125281716 32.386536230303705,119.4348125281716 32.38638602659887,119.436325294056 32.38645039961523,119.43616436151511 32.388295759417474,119.43617509035117 32.388800014712274,119.43618581918723 32.38881074354833))",
    "remark": "第十网格",
    "zoom": 10
}, {
    "centerX": "119.43490007623525",
    "centerY": "32.39281997527114",
    "count": 0,
    "createDate": "2018-09-21 15:31:34",
    "createUser": "Dyzgldg001",
    "gisType": "3D",
    "id": 39679,
    "isDeleted": 0,
    "maxLat": 32.395405624761494,
    "maxLon": 119.43589249357076,
    "minLat": 32.39223525370589,
    "minLon": 119.43432608350606,
    "orgInternalCode": ".1.10.1.1.5.2.",
    "organization": {
        "createDate": "2015-12-22 17:25:33",
        "createUser": "Dyzgldg001",
        "departmentNo": "321002001006001",
        "fullPinyin": "dierwangge",
        "gridGatetory": 0,
        "gridProperty": 0,
        "gridPropertyLabel": "城市网格",
        "hasJudgeAuthorize": false,
        "homePageVersion": 0,
        "id": 136956,
        "maxCode": 0,
        "navigationVersion": 1,
        "newDepartmentNo": "321002001006002",
        "orgInternalCode": ".1.10.1.1.5.2.",
        "orgLevel": {
            "displaySeq": 0,
            "id": 207,
            "internalId": 0
        },
        "orgName": "第二网格",
        "orgType": {
            "displaySeq": 0,
            "id": 214,
            "internalId": 0
        },
        "parentOrg": {
            "gridPropertyLabel": "城市网格",
            "id": 21199,
            "maxCode": 0
        },
        "seq": 2,
        "simplePinyin": "dewg",
        "subCount": 0,
        "subCountFun": 0,
        "updateDate": "2019-07-25 16:20:07",
        "updateUser": "Byzgl001"
    },
    "points": "POLYGON((119.43432608350606 32.39226744021407,119.43435290559621 32.39223525370589,119.43484106763692 32.39224061812392,119.43499663575979 32.39234790648452,119.43589249357076 32.392648313894185,119.43580129846426 32.393367145910176,119.43569401010366 32.39423081721297,119.43554917081686 32.39531442965499,119.43508246644826 32.395405624761494,119.43488398298116 32.39470288599959,119.43506637319418 32.39449367369643,119.43516293271871 32.39402696932784,119.43512001737447 32.39395186747542,119.43510928853841 32.39375874842635,119.43519511922689 32.393672917737874,119.43516829713674 32.39330813731185,119.43463721975179 32.39326522196761,119.4343314479241 32.39309356059066,119.43435827001424 32.39226744021407,119.43434217676015 32.39228353346816,119.43434754117818 32.39228353346816,119.43435290559621 32.39226207579604,119.43434754117818 32.39226207579604,119.43441727861257 32.39233717764846,119.43432608350606 32.39226744021407))",
    "remark": "第二网格",
    "zoom": 10
}, {
    "centerX": "119.43361272066011",
    "centerY": "32.393738424302036",
    "count": 0,
    "createDate": "2018-09-21 15:33:32",
    "createUser": "Dyzgldg001",
    "gisType": "3D",
    "id": 39688,
    "isDeleted": 0,
    "maxLat": 32.39539066505521,
    "maxLon": 119.43421353547944,
    "minLat": 32.39131370735257,
    "minLon": 119.43318356721772,
    "orgInternalCode": ".1.10.1.1.5.3.",
    "organization": {
        "createDate": "2015-12-22 17:25:42",
        "createUser": "Dyzgldg001",
        "departmentNo": "321002001006002",
        "fullPinyin": "disanwangge",
        "gridGatetory": 0,
        "gridProperty": 0,
        "gridPropertyLabel": "城市网格",
        "hasJudgeAuthorize": false,
        "homePageVersion": 0,
        "id": 136957,
        "maxCode": 0,
        "navigationVersion": 1,
        "newDepartmentNo": "321002001006003",
        "orgInternalCode": ".1.10.1.1.5.3.",
        "orgLevel": {
            "displaySeq": 0,
            "id": 207,
            "internalId": 0
        },
        "orgName": "第三网格",
        "orgType": {
            "displaySeq": 0,
            "id": 214,
            "internalId": 0
        },
        "parentOrg": {
            "gridPropertyLabel": "城市网格",
            "id": 21199,
            "maxCode": 0
        },
        "seq": 3,
        "simplePinyin": "dswg",
        "subCount": 0,
        "subCountFun": 0,
        "updateDate": "2019-07-25 16:20:07",
        "updateUser": "Byzgl001"
    },
    "points": "POLYGON((119.43322648256196 32.39487568092435,119.43318356721772 32.39131370735257,119.43363417833223 32.39133516502469,119.43367709367647 32.3916784877786,119.43376292436494 32.39238659095853,119.4337200090207 32.394746934891636,119.43421353547944 32.394768392563755,119.43421353547944 32.39536920738309,119.43376292436494 32.39539066505521,119.43361272066011 32.39491859626859,119.4332693979062 32.39487568092435,119.43322648256196 32.39487568092435))",
    "remark": "第三网格",
    "zoom": 10
}, {
    "centerX": "119.43421732861741",
    "centerY": "32.38996632846411",
    "count": 0,
    "createDate": "2018-09-21 15:39:44",
    "createUser": "Dyzgldg001",
    "gisType": "3D",
    "id": 39716,
    "isDeleted": 0,
    "maxLat": 32.39078172000464,
    "maxLon": 119.43507563550217,
    "minLat": 32.388614495120606,
    "minLon": 119.43356286961777,
    "orgInternalCode": ".1.10.1.1.5.6.",
    "organization": {
        "createDate": "2015-12-22 17:26:03",
        "createUser": "Dyzgldg001",
        "departmentNo": "321002001006005",
        "fullPinyin": "diliuwangge",
        "gridGatetory": 0,
        "gridProperty": 0,
        "gridPropertyLabel": "城市网格",
        "hasJudgeAuthorize": false,
        "homePageVersion": 0,
        "id": 136960,
        "maxCode": 0,
        "navigationVersion": 1,
        "newDepartmentNo": "321002001006006",
        "orgInternalCode": ".1.10.1.1.5.6.",
        "orgLevel": {
            "displaySeq": 0,
            "id": 207,
            "internalId": 0
        },
        "orgName": "第六网格",
        "orgType": {
            "displaySeq": 0,
            "id": 214,
            "internalId": 0
        },
        "parentOrg": {
            "gridPropertyLabel": "城市网格",
            "id": 21199,
            "maxCode": 0
        },
        "seq": 6,
        "simplePinyin": "dlwg",
        "subCount": 0,
        "subCountFun": 0,
        "updateDate": "2019-07-25 16:20:07",
        "updateUser": "Byzgl001"
    },
    "points": "POLYGON((119.43372380215867 32.39070661815222,119.43356286961777 32.38960154803809,119.43356286961777 32.389129479251466,119.43362724263413 32.388614495120606,119.43473231274827 32.38874324115332,119.43463575322373 32.38935478480872,119.43463575322373 32.3898375824314,119.43463575322373 32.390663702807984,119.43507563550217 32.39069588931616,119.43507563550217 32.39078172000464,119.43371307332261 32.39074953349646,119.43372380215867 32.39070661815222))",
    "remark": "第六网格",
    "zoom": 10
}, {
    "centerX": "119.43543473725416",
    "centerY": "32.38967861366512",
    "count": 0,
    "createDate": "2018-09-21 15:42:10",
    "createUser": "Dyzgldg001",
    "gisType": "3D",
    "id": 39731,
    "isDeleted": 0,
    "maxLat": 32.39069785309078,
    "maxLon": 119.43620721345044,
    "minLat": 32.38694276046993,
    "minLon": 119.43379322533704,
    "orgInternalCode": ".1.10.1.1.5.7.",
    "organization": {
        "createDate": "2015-12-22 17:26:11",
        "createUser": "Dyzgldg001",
        "departmentNo": "321002001006006",
        "fullPinyin": "diqiwangge",
        "gridGatetory": 0,
        "gridProperty": 0,
        "gridPropertyLabel": "城市网格",
        "hasJudgeAuthorize": false,
        "homePageVersion": 0,
        "id": 136961,
        "maxCode": 0,
        "navigationVersion": 1,
        "newDepartmentNo": "321002001006007",
        "orgInternalCode": ".1.10.1.1.5.7.",
        "orgLevel": {
            "displaySeq": 0,
            "id": 207,
            "internalId": 0
        },
        "orgName": "第七网格",
        "orgType": {
            "displaySeq": 0,
            "id": 214,
            "internalId": 0
        },
        "parentOrg": {
            "gridPropertyLabel": "城市网格",
            "id": 21199,
            "maxCode": 0
        },
        "seq": 7,
        "simplePinyin": "dqwg",
        "subCount": 0,
        "subCountFun": 0,
        "updateDate": "2019-07-25 16:20:07",
        "updateUser": "Byzgl001"
    },
    "points": "POLYGON((119.43607846741773 32.3906656665826,119.43512360100843 32.39069785309078,119.43468371872999 32.39063348007442,119.43467298989393 32.38985027504207,119.43466226105787 32.38947476577999,119.43471590523816 32.389013425829425,119.43476954941846 32.388777391436115,119.43495193963147 32.388777391436115,119.4349733973036 32.38856281471492,119.43512360100843 32.38843406868221,119.43483392243482 32.38815511894466,119.43461934571363 32.38796199989559,119.43440476899244 32.387253896715656,119.43435112481214 32.387039319994464,119.43379322533704 32.387007133486286,119.43379322533704 32.38694276046993,119.43437258248426 32.38698567581417,119.4346515322218 32.38790835571529,119.43523088936902 32.38846625519039,119.4356600428114 32.38868083191158,119.43613211159803 32.38882030678035,119.43620721345044 32.38891686630489,119.43607846741773 32.3906656665826))",
    "remark": "第七网格",
    "zoom": 10
}, {
    "centerX": "119.43414849260796",
    "centerY": "32.38747137923068",
    "count": 0,
    "createDate": "2018-09-21 15:47:36",
    "createUser": "Dyzgldg001",
    "gisType": "3D",
    "id": 39758,
    "isDeleted": 0,
    "maxLat": 32.38875883955783,
    "maxLon": 119.43515700319756,
    "minLat": 32.38506811995334,
    "minLon": 119.43361205080498,
    "orgInternalCode": ".1.10.1.1.5.9.",
    "organization": {
        "createDate": "2015-12-22 17:26:30",
        "createUser": "Dyzgldg001",
        "departmentNo": "321002001006008",
        "fullPinyin": "dijiuwangge",
        "gridGatetory": 0,
        "gridProperty": 0,
        "gridPropertyLabel": "城市网格",
        "hasJudgeAuthorize": false,
        "homePageVersion": 0,
        "id": 136963,
        "maxCode": 0,
        "navigationVersion": 1,
        "newDepartmentNo": "321002001006009",
        "orgInternalCode": ".1.10.1.1.5.9.",
        "orgLevel": {
            "displaySeq": 0,
            "id": 207,
            "internalId": 0
        },
        "orgName": "第九网格",
        "orgType": {
            "displaySeq": 0,
            "id": 214,
            "internalId": 0
        },
        "parentOrg": {
            "gridPropertyLabel": "城市网格",
            "id": 21199,
            "maxCode": 0
        },
        "seq": 9,
        "simplePinyin": "djwg",
        "subCount": 0,
        "subCountFun": 0,
        "updateDate": "2019-07-25 16:19:59",
        "updateUser": "Byzgl001"
    },
    "points": "POLYGON((119.43383735636223 32.38703149695224,119.43430942514885 32.38706368346042,119.43456691721428 32.387889803837005,119.43488878229607 32.38827604193515,119.43511408785332 32.3884477033121,119.43494242647637 32.38853353400058,119.43492096880425 32.38875883955783,119.43362277964104 32.38858717818088,119.43375152567376 32.38703149695224,119.4336871526574 32.38599079985446,119.43361205080498 32.3855831040842,119.43430942514885 32.385164679477874,119.43457764605034 32.38508957762546,119.43515700319756 32.38506811995334,119.4351462743615 32.385164679477874,119.43442744234551 32.38521832365817,119.43405193308342 32.385411442707245,119.43383735636223 32.385626019428436,119.43386954287041 32.38607663054294,119.4347493074273 32.38606590170688,119.43476003626336 32.38650578398532,119.43477076509942 32.38661307234592,119.43456691721428 32.386655987690155,119.43437379816521 32.38661307234592,119.43383735636223 32.386623801181976,119.433794441018 32.386623801181976,119.43380516985405 32.38703149695224,119.43383735636223 32.38703149695224))",
    "remark": "第九网格",
    "zoom": 10
}, {
    "centerX": "119.4346069821886",
    "centerY": "32.391157117474314",
    "count": 0,
    "createDate": "2018-09-21 15:36:57",
    "createUser": "Dyzgldg001",
    "gisType": "3D",
    "id": 39702,
    "isDeleted": 0,
    "maxLat": 32.394730953429956,
    "maxLon": 119.43607425527175,
    "minLat": 32.39071836874368,
    "minLon": 119.43306202979602,
    "orgInternalCode": ".1.10.1.1.5.4.",
    "organization": {
        "createDate": "2015-12-22 17:25:47",
        "createUser": "Dyzgldg001",
        "departmentNo": "321002001006003",
        "fullPinyin": "disiwangge",
        "gridGatetory": 0,
        "gridProperty": 0,
        "gridPropertyLabel": "城市网格",
        "hasJudgeAuthorize": false,
        "homePageVersion": 0,
        "id": 136958,
        "maxCode": 0,
        "navigationVersion": 1,
        "newDepartmentNo": "321002001006004",
        "orgInternalCode": ".1.10.1.1.5.4.",
        "orgLevel": {
            "displaySeq": 0,
            "id": 207,
            "internalId": 0
        },
        "orgName": "第四网格",
        "orgType": {
            "displaySeq": 0,
            "id": 214,
            "internalId": 0
        },
        "parentOrg": {
            "gridPropertyLabel": "城市网格",
            "id": 21199,
            "maxCode": 0
        },
        "seq": 4,
        "simplePinyin": "dswg",
        "subCount": 0,
        "subCountFun": 0,
        "updateDate": "2019-07-25 16:20:07",
        "updateUser": "Byzgl001"
    },
    "points": "POLYGON((119.43319892720778 32.39071836874368,119.43358516530593 32.390804199432154,119.4354519827803 32.390782741760034,119.43607425527175 32.390761284087915,119.43592405156691 32.391533760284204,119.43583822087844 32.392499355529566,119.43521594838698 32.39241352484109,119.43474387960036 32.39222040579202,119.4343361838301 32.3921989481199,119.43418598012526 32.392778305267115,119.43416452245314 32.39316454336526,119.4343361838301 32.39359369680764,119.43440055684646 32.39413013861062,119.43463659123977 32.394237426971216,119.43448638753493 32.39447346136453,119.43429326848586 32.39470949575784,119.4338855727156 32.394730953429956,119.43369245366652 32.39464512274148,119.43379974202712 32.39294996664407,119.43382119969924 32.39237060949685,119.43371391133864 32.39161959097268,119.43374867530383 32.39145752488398,119.43310494514026 32.39132877885127,119.43306202979602 32.390899625408885,119.43319892720778 32.39071836874368))",
    "remark": "第四网格",
    "zoom": 10
}, {
    "centerX": "119.4352840731982",
    "centerY": "32.38559983603651",
    "count": 0,
    "createDate": "2018-09-21 15:49:31",
    "createUser": "wh077",
    "gisType": "3D",
    "id": 39767,
    "isDeleted": 0,
    "maxLat": 32.3864259564131,
    "maxLon": 119.43646424516476,
    "minLat": 32.385041936561414,
    "minLon": 119.4338785956744,
    "orgInternalCode": ".1.10.1.1.5.11.",
    "organization": {
        "createDate": "2018-04-28 16:43:21",
        "createUser": "wh077",
        "departmentNo": "321002001006010",
        "fullPinyin": "dishiyiwangge",
        "gridGatetory": 0,
        "gridProperty": 0,
        "gridPropertyLabel": "城市网格",
        "hasJudgeAuthorize": false,
        "homePageVersion": 0,
        "id": 175712,
        "maxCode": 0,
        "navigationVersion": 1,
        "newDepartmentNo": "321002001006011",
        "orgInternalCode": ".1.10.1.1.5.11.",
        "orgLevel": {
            "displaySeq": 0,
            "id": 207,
            "internalId": 0
        },
        "orgName": "第十一网格",
        "orgType": {
            "displaySeq": 0,
            "id": 214,
            "internalId": 0
        },
        "parentOrg": {
            "gridPropertyLabel": "城市网格",
            "id": 21199,
            "maxCode": 0
        },
        "seq": 11,
        "simplePinyin": "dsywg",
        "subCount": 0,
        "subCountFun": 0,
        "updateDate": "2019-07-25 16:19:42",
        "updateUser": "Byzgl001"
    },
    "points": "POLYGON((119.43520897134579 32.385041936561414,119.43646424516476 32.385041936561414,119.43635695680416 32.3864259564131,119.43481200441158 32.38639376990492,119.43473690255917 32.38607190482313,119.43391078218258 32.386039718314954,119.4338785956744 32.38565348021681,119.43440430864132 32.385267242118665,119.43515532716549 32.38519214026625,119.4352304290179 32.38506339423353,119.4352304290179 32.38506339423353,119.4352304290179 32.38509558074171,119.43520897134579 32.385041936561414))",
    "remark": "第十一网格",
    "zoom": 10
}, {
    "centerX": "119.43446287616354",
    "centerY": "32.3955397352118",
    "count": 0,
    "createDate": "2018-09-21 15:27:47",
    "createUser": "admin",
    "gisType": "3D",
    "id": 39660,
    "isDeleted": 0,
    "maxLat": 32.39605471934266,
    "maxLon": 119.4355357597695,
    "minLat": 32.392279302597494,
    "minLon": 119.43323463394101,
    "orgInternalCode": ".1.10.1.1.5.1.",
    "organization": {
        "createDate": "2014-12-02 15:59:48",
        "createUser": "admin",
        "departmentNo": "321002001006000",
        "fullPinyin": "diyiwangge",
        "gridGatetory": 0,
        "gridProperty": 0,
        "gridPropertyLabel": "城市网格",
        "hasJudgeAuthorize": false,
        "homePageVersion": 0,
        "id": 64847,
        "maxCode": 0,
        "navigationVersion": 1,
        "newDepartmentNo": "321002001006001",
        "orgInternalCode": ".1.10.1.1.5.1.",
        "orgLevel": {
            "displaySeq": 0,
            "id": 207,
            "internalId": 0
        },
        "orgName": "第一网格",
        "orgType": {
            "displaySeq": 0,
            "id": 214,
            "internalId": 0
        },
        "parentOrg": {
            "gridPropertyLabel": "城市网格",
            "id": 21199,
            "maxCode": 0
        },
        "seq": 1,
        "simplePinyin": "dywg",
        "subCount": 0,
        "subCountFun": 0,
        "updateDate": "2019-07-25 16:20:07",
        "updateUser": "Byzgl001"
    },
    "points": "POLYGON((119.43324536277707 32.39601407109447,119.43323463394101 32.39493045865245,119.43364232971128 32.394909000980334,119.43373888923581 32.39534888325878,119.4337521955266 32.39544430923507,119.43426717965745 32.39544430923507,119.43431009500169 32.39478985023543,119.43446029870653 32.3946932907109,119.43453540055894 32.39437142562911,119.43452467172288 32.39432851028487,119.43471779077196 32.39430705261275,119.43473924844407 32.39411393356368,119.4344388410344 32.394017374039144,119.43437446801805 32.39356676292464,119.43424572198533 32.39311615181014,119.43422426431322 32.39308396530196,119.4342564508214 32.39283720207259,119.43428863732957 32.392279302597494,119.43434228150987 32.39231148910567,119.43431009500169 32.39310542297408,119.43447102754259 32.3931805248265,119.43457831590318 32.393266355514974,119.43478216378831 32.393277084351034,119.4351576730504 32.39330927085921,119.43518985955858 32.39354530525252,119.43518985955858 32.3936847801213,119.4351040288701 32.393727695465536,119.43511475770616 32.39394227218673,119.43516840188646 32.393985187530966,119.43513621537828 32.3940817470555,119.43511475770616 32.39429632377669,119.4351040288701 32.39443579864547,119.4348705719338 32.394659970654914,119.43495640262228 32.3949818357367,119.43506369098287 32.395410989179084,119.4355357597695 32.395346616162726,119.43544992908102 32.39605471934266,119.43540701373678 32.39603326167054,119.43324536277707 32.39601407109447))",
    "remark": "第一网格",
    "zoom": 10
}, {
    "centerX": "119.43352563294758",
    "centerY": "32.390001915615706",
    "count": 0,
    "createDate": "2018-09-21 15:38:20",
    "createUser": "Dyzgldg001",
    "gisType": "3D",
    "id": 39708,
    "isDeleted": 0,
    "maxLat": 32.39069505908935,
    "maxLon": 119.43359815734298,
    "minLat": 32.388377630500486,
    "minLon": 119.43321191924484,
    "orgInternalCode": ".1.10.1.1.5.5.",
    "organization": {
        "createDate": "2015-12-22 17:25:56",
        "createUser": "Dyzgldg001",
        "departmentNo": "321002001006004",
        "fullPinyin": "diwuwangge",
        "gridGatetory": 0,
        "gridProperty": 0,
        "gridPropertyLabel": "城市网格",
        "hasJudgeAuthorize": false,
        "homePageVersion": 0,
        "id": 136959,
        "maxCode": 0,
        "navigationVersion": 1,
        "newDepartmentNo": "321002001006005",
        "orgInternalCode": ".1.10.1.1.5.5.",
        "orgLevel": {
            "displaySeq": 0,
            "id": 207,
            "internalId": 0
        },
        "orgName": "第五网格",
        "orgType": {
            "displaySeq": 0,
            "id": 214,
            "internalId": 0
        },
        "parentOrg": {
            "gridPropertyLabel": "城市网格",
            "id": 21199,
            "maxCode": 0
        },
        "seq": 5,
        "simplePinyin": "dwwg",
        "subCount": 0,
        "subCountFun": 0,
        "updateDate": "2019-07-25 16:20:07",
        "updateUser": "Byzgl001"
    },
    "points": "POLYGON((119.4332762922612 32.390630686072996,119.43329774993332 32.3899654982373,119.43321191924484 32.389429056434324,119.43325483458908 32.388377630500486,119.43351232665451 32.388420545844724,119.43349086898239 32.38955780246704,119.43359815734298 32.39056631305664,119.43357669967087 32.39069505908935,119.43355524199875 32.390673601417234,119.4332762922612 32.390630686072996))",
    "remark": "第五网格",
    "zoom": 10
}, {
    "centerX": "119.43345711119414",
    "centerY": "32.387808092226344",
    "count": 0,
    "createDate": "2018-09-21 15:45:16",
    "createUser": "Dyzgldg001",
    "gisType": "3D",
    "id": 39746,
    "isDeleted": 0,
    "maxLat": 32.39069641622198,
    "maxLon": 119.43369314558745,
    "minLat": 32.38557649432595,
    "minLon": 119.43309790469016,
    "orgInternalCode": ".1.10.1.1.5.8.",
    "organization": {
        "createDate": "2015-12-22 17:28:59",
        "createUser": "Dyzgldg001",
        "departmentNo": "321002001006007",
        "fullPinyin": "dibawangge",
        "gridGatetory": 0,
        "gridProperty": 0,
        "gridPropertyLabel": "城市网格",
        "hasJudgeAuthorize": false,
        "homePageVersion": 0,
        "id": 136962,
        "maxCode": 0,
        "navigationVersion": 1,
        "newDepartmentNo": "321002001006008",
        "orgInternalCode": ".1.10.1.1.5.8.",
        "orgLevel": {
            "displaySeq": 0,
            "id": 207,
            "internalId": 0
        },
        "orgName": "第八网格",
        "orgType": {
            "displaySeq": 0,
            "id": 214,
            "internalId": 0
        },
        "parentOrg": {
            "gridPropertyLabel": "城市网格",
            "id": 21199,
            "maxCode": 0
        },
        "seq": 8,
        "simplePinyin": "dbwg",
        "subCount": 0,
        "subCountFun": 0,
        "updateDate": "2019-07-25 16:20:07",
        "updateUser": "Byzgl001"
    },
    "points": "POLYGON((119.43326956606711 32.39069641622198,119.43309790469016 32.3906642297138,119.43313524611236 32.38822651683267,119.43318889029266 32.38713217555459,119.43321034796477 32.38571596919473,119.43356439955474 32.38557649432595,119.43369314558745 32.38637042819436,119.43365023024322 32.387990482439356,119.43359658606292 32.38844109355386,119.43324253447295 32.38835526286538,119.4331781614566 32.38935304461892,119.43325326330901 32.389750011553126,119.43326399214507 32.39067269145425,119.43326956606711 32.39069641622198))",
    "remark": "第八网格",
    "zoom": 10
}]